mongfontbuilder/__init__.py
mongfontbuilder/__main__.py
mongfontbuilder/data/README.md
mongfontbuilder/data/__init__.py
mongfontbuilder/data/aliases.json
mongfontbuilder/data/ligatures.json
mongfontbuilder/data/locales.json
mongfontbuilder/data/misc.py
mongfontbuilder/data/particles.json
mongfontbuilder/data/types.py
mongfontbuilder/data/variants.json
mongfontbuilder/data/writtenUnits.json
mongfontbuilder/otl.py
mongfontbuilder/utils.py
mongfontbuilder-0.6.6.dist-info/WHEEL
mongfontbuilder-0.6.6.dist-info/METADATA
mongfontbuilder-0.6.6.dist-info/RECORD
