Metadata-Version: 2.3
Name: mongfontbuilder
Version: 0.6.6
Summary: Mongolian Font Builder.
Author: Kushim Jiang, Liang Hai
Author-email: Kushim Jiang <kushim_jiang@outlook.com>, Liang Hai <lianghai@gmail.com>
License: MIT
Requires-Dist: cattrs>=24.1.2
Requires-Dist: pyyaml>=6.0.1
Requires-Dist: tptq-feacomposer>=1.5.0
Requires-Dist: ufo2ft>=3.4.3
Requires-Dist: ufolib2>=0.17.1
Requires-Dist: ufonormalizer>=0.6.2
Requires-Dist: unicodedata2>=16.0.0
Requires-Dist: babelfont>=3.1.3
Requires-Python: >=3.10
Project-URL: releasenotes, https://github.com/Kushim-Jiang/mongfontbuilder/releases
Project-URL: repository, https://github.com/Kushim-Jiang/mongfontbuilder
